{
  "version": "3.0",
  "generated": "2026-03-17T18:50:42Z",
  "data_repo": {
    "commit": "97f9aa0979fcaf1c0598d69dba015dfbe069cbb7",
    "commit_short": "97f9aa0",
    "branch": "main",
    "commit_date": "2026-03-17T18:34:54Z",
    "dirty": true
  },
  "pipeline": {
    "gather": {
      "last_run": "2026-03-17T18:50:17Z",
      "sources": {
        "beta": {
          "last_fetch": "2026-03-17T18:50:14Z",
          "current_hash": "4a238b51501857e372a75ed477e9ed188f38382e155f7dadcc8523460d91e9c4",
          "previous_hash": "3f3862b35ad743e72915d83b27c5cd5354fd99ca600b03182c7fa06fc87737c9",
          "changed": true
        },
        "gdmf": {
          "last_fetch": "2026-03-17T18:50:13Z",
          "current_hash": "ef73b292ddece7701180ff7894943426603893f0b539b8fc59168b9afae6ce6a",
          "previous_hash": "5ed5f865864899cf8b6a5ca449e1d08d372fb87dd2475b3435b291de9b65f2d8",
          "changed": true
        },
        "ipsw": {
          "last_fetch": "2026-03-17T18:50:14Z",
          "current_hash": "d6a04b622f71f0ec0fdfdaef6fcbcce45f13ff95aabad6eb8a8bea13a2b377ab",
          "previous_hash": "71f2453a5a580a0e944bed78fac28386039f9f99f7a6081ba833a3f775e7ffe7",
          "changed": true
        },
        "kev": {
          "last_fetch": "2026-03-17T18:50:12Z",
          "current_hash": "1ee81a770dc0a25ca15755a2276a8e6481b7455473ad6ad0e38ceef1b080a1ff",
          "previous_hash": "d5fc20d8fdb8af7d7df73af60c61a83c4c54ac8d6420fcc2df061ce9e8dd4a16",
          "changed": true
        },
        "uma": {
          "last_fetch": "2026-03-17T18:50:16Z",
          "current_hash": "f1ccfb687a776e8af1e7d9048f17236d3f9c6db256ea77051c758417871e7c39",
          "previous_hash": "f1ccfb687a776e8af1e7d9048f17236d3f9c6db256ea77051c758417871e7c39",
          "changed": false
        },
        "xprotect": {
          "last_fetch": "2026-03-17T18:50:17Z",
          "current_hash": "daa16ba4aa3ca163f5bbdc8efcdf1b4ba3a49876eae8a87447ef6fb740fa5893",
          "previous_hash": "daa16ba4aa3ca163f5bbdc8efcdf1b4ba3a49876eae8a87447ef6fb740fa5893",
          "changed": false
        }
      },
      "changes_detected": [
        "beta",
        "gdmf",
        "ipsw",
        "kev"
      ]
    },
    "fetch": {
      "last_run_start": "2026-03-17T18:50:17Z",
      "last_run_end": "2026-03-17T18:50:41Z",
      "mode": "online",
      "releases_fetched": 660,
      "current_hash": "d462902a512b9594296f55339faeef809053321996ac55ee348a7cf29cfb9cd9",
      "previous_hash": "4b578a6cb4b345fe287fb5b0c4eb5bd7ccf92ec0065cf5d7e6879e662cee1a76",
      "performance_stats": "26.96 releases/sec"
    },
    "build": {
      "last_run": "2026-03-17T18:50:42Z",
      "v1": {
        "last_run": "2026-03-17T18:50:42Z",
        "platforms": {
          "ios": {
            "current_hash": "90387b1c7242babbb5089155586889c048f1d22e694785d0ad4fbeaf2e7add5f",
            "previous_hash": null,
            "entries": 3,
            "size_bytes": 70852,
            "last_updated": "2026-03-17T18:50:42Z"
          },
          "macos": {
            "current_hash": "a5e12e9a25a6de30ac356580bf6251b35a89cb28d555bb1114089ec3f01a05be",
            "previous_hash": null,
            "entries": 5,
            "size_bytes": 422567,
            "last_updated": "2026-03-17T18:50:42Z"
          },
          "safari": {
            "current_hash": "5519d49cc34ad7efa343e9b1f49493979f977102d6468639468b19c0982c2296",
            "previous_hash": null,
            "entries": 3,
            "size_bytes": 38264,
            "last_updated": "2026-03-17T18:50:42Z"
          },
          "tvos": {
            "current_hash": "9eb5f53c635bb426a8054ebefe189a0197dc557eaba1cb5275fe2d0910284b07",
            "previous_hash": null,
            "entries": 2,
            "size_bytes": 27071,
            "last_updated": "2026-03-17T18:50:42Z"
          },
          "visionos": {
            "current_hash": "2d20844b22ca23c56eeaf44e6f74047f644b6094b5185fc4f484afa9763f46ab",
            "previous_hash": null,
            "entries": 2,
            "size_bytes": 31922,
            "last_updated": "2026-03-17T18:50:42Z"
          },
          "watchos": {
            "current_hash": "dfdcea7228fa55500e48520056d4cb14ffea61ed80b414a986f45f98026a8e29",
            "previous_hash": null,
            "entries": 0,
            "size_bytes": 126,
            "last_updated": "2026-03-17T18:50:42Z"
          }
        }
      },
      "v2": {
        "last_run": "2026-03-17T18:50:42Z",
        "platforms": {
          "ios": {
            "current_hash": "a9a2dc4fc89667fe7df9c220d7ab8f6e20b4e3822b976ca4b66d2ef82ed60382",
            "previous_hash": null,
            "entries": 3,
            "size_bytes": 140308,
            "last_updated": "2026-03-17T18:50:42Z"
          },
          "macos": {
            "current_hash": "62fbe627463eec7661b65129c3bcee0f73c19bab1735e3bb61bedcb44e58679d",
            "previous_hash": null,
            "entries": 5,
            "size_bytes": 507399,
            "last_updated": "2026-03-17T18:50:42Z"
          },
          "safari": {
            "current_hash": "5519d49cc34ad7efa343e9b1f49493979f977102d6468639468b19c0982c2296",
            "previous_hash": null,
            "entries": 3,
            "size_bytes": 38264,
            "last_updated": "2026-03-17T18:50:42Z"
          },
          "tvos": {
            "current_hash": "146aef31b184c52684ee2f52d9c72407d792ee5f79f47ccd6dca0739f50d5b36",
            "previous_hash": null,
            "entries": 2,
            "size_bytes": 33512,
            "last_updated": "2026-03-17T18:50:42Z"
          },
          "visionos": {
            "current_hash": "641cd62b2f23c7558776b1b0e8145a9a692ffc407ef51592230b29e00e6cc67a",
            "previous_hash": null,
            "entries": 2,
            "size_bytes": 38964,
            "last_updated": "2026-03-17T18:50:42Z"
          },
          "watchos": {
            "current_hash": "bf7807a95c1824ad575ee87dd81161114ab952e94f40e8fe9b34b4259f1ea90f",
            "previous_hash": null,
            "entries": 2,
            "size_bytes": 42595,
            "last_updated": "2026-03-17T18:50:42Z"
          }
        }
      }
    },
    "bulletin": {
      "last_run": "2026-03-17T18:50:42Z",
      "bulletin_count": 1,
      "cve_count": 25,
      "status": "completed",
      "current_hash": "9f85c9f38ad60be96a3ee63e6ffd0ba0c5d1d397c6653dbe35f3cb8719830c55",
      "previous_hash": "4da55d980aee6fd1aa51e87ebd05609b1e37cccf4176461d0c891e1f34346d36",
      "live_check_enabled": false
    },
    "enrich": null
  }
}